vital_agent_template/__init__.py
vital_agent_template/vital_agent_fastapi_app.py
vital_agent_template-0.1.1.dist-info/LICENSE
vital_agent_template-0.1.1.dist-info/METADATA
vital_agent_template-0.1.1.dist-info/WHEEL
vital_agent_template-0.1.1.dist-info/top_level.txt
vital_agent_template-0.1.1.dist-info/RECORD
